kfactory/__init__.py
kfactory/conf.py
kfactory/cross_section.py
kfactory/decorators.py
kfactory/enclosure.py
kfactory/exceptions.py
kfactory/geometry.py
kfactory/grid.py
kfactory/instance.py
kfactory/instance_group.py
kfactory/instance_pins.py
kfactory/instance_ports.py
kfactory/instances.py
kfactory/kcell.py
kfactory/layer.py
kfactory/layout.py
kfactory/merge.py
kfactory/netlist.py
kfactory/packing.py
kfactory/pin.py
kfactory/pins.py
kfactory/placer.py
kfactory/port.py
kfactory/ports.py
kfactory/protocols.py
kfactory/py.typed
kfactory/schematic.py
kfactory/serialization.py
kfactory/session_cache.py
kfactory/settings.py
kfactory/shapes.py
kfactory/typings.py
kfactory/utilities.py
kfactory/cells/__init__.py
kfactory/cells/_demopdk.py
kfactory/cells/bezier.py
kfactory/cells/circular.py
kfactory/cells/euler.py
kfactory/cells/straight.py
kfactory/cells/taper.py
kfactory/cells/virtual/__init__.py
kfactory/cells/virtual/circular.py
kfactory/cells/virtual/euler.py
kfactory/cells/virtual/straight.py
kfactory/cli/__init__.py
kfactory/cli/build.py
kfactory/factories/__init__.py
kfactory/factories/bezier.py
kfactory/factories/circular.py
kfactory/factories/euler.py
kfactory/factories/straight.py
kfactory/factories/taper.py
kfactory/factories/virtual/__init__.py
kfactory/factories/virtual/circular.py
kfactory/factories/virtual/euler.py
kfactory/factories/virtual/straight.py
kfactory/factories/virtual/utils.py
kfactory/routing/__init__.py
kfactory/routing/electrical.py
kfactory/routing/generic.py
kfactory/routing/length_functions.py
kfactory/routing/manhattan.py
kfactory/routing/optical.py
kfactory/routing/steps.py
kfactory/routing/aa/__init__.py
kfactory/routing/aa/optical.py
kfactory/technology/__init__.py
kfactory/technology/layer_map.py
kfactory/utils/__init__.py
kfactory/utils/difftest.py
kfactory/utils/fill.py
kfactory/utils/simplify.py
kfactory/utils/violations.py
kfactory/widgets/__init__.py
kfactory/widgets/interactive.py
kfactory-2.3.0.dist-info/licenses/LICENSE
kfactory-2.3.0.dist-info/METADATA
kfactory-2.3.0.dist-info/WHEEL
kfactory-2.3.0.dist-info/entry_points.txt
kfactory-2.3.0.dist-info/top_level.txt
kfactory-2.3.0.dist-info/RECORD
